autograder/__init__.py
autograder/core.py
autograder/interactive.py
autograder_js-0.1.11.dist-info/METADATA
autograder_js-0.1.11.dist-info/WHEEL
autograder_js-0.1.11.dist-info/top_level.txt
autograder_js-0.1.11.dist-info/RECORD
